behoof/__init__.py
behoof/matrixXY.py
behoof/utils_code.py
behoof-1.2.dist-info/METADATA
behoof-1.2.dist-info/WHEEL
behoof-1.2.dist-info/top_level.txt
behoof-1.2.dist-info/RECORD
