Metadata-Version: 2.1
Name: behoof
Version: 1.2
Summary: A general-purpose utility library offering a wide range of functions
Home-page: https://github.com/pascal65536/behoof
Author: Sergey V. Pakhtusov
Author-email: pascal65536@gmail.com
Requires-Python: >=3.10
Dynamic: author
Dynamic: author-email
Dynamic: description
Dynamic: description-content-type
Dynamic: home-page
Dynamic: requires-python
Dynamic: summary
